{
  "postal_code": "97675",
  "addresses": [
    "Hannulantie 3",
    "Hannulantie 10",
    "Hannulantie 37",
    "Hannulantie",
    "Huhtasaarentie 69",
    "Huhtasaarentie 71",
    "Huhtasaarentie 75",
    "Huhtasaarentie 76",
    "Huhtasaarentie 77",
    "Huhtasaarentie",
    "Isopalolammentie 126",
    "Isopalolammentie",
    "Jokelantie 5",
    "Jokelantie 38",
    "Jokelantie 43",
    "Jokelantie 84",
    "Jokelantie 86",
    "Jokelantie 98",
    "Jokelantie 100",
    "Jokelantie 109",
    "Jokelantie 120",
    "Jokelantie 128",
    "Jokelantie 145",
    "Jokelantie 146",
    "Jokelantie 166",
    "Jokelantie 174",
    "Jokelantie 175",
    "Jokelantie 176",
    "Jokelantie 178",
    "Jokelantie 180",
    "Jokelantie 182",
    "Jokelantie 188",
    "Jokelantie 190",
    "Jokelantie 210",
    "Jokelantie 212",
    "Jokelantie 222",
    "Jokelantie 236",
    "Jokelantie 619",
    "Jokelantie 639",
    "Jokelantie 1468",
    "Jokelantie 1533",
    "Jokelantie 1547",
    "Jokelantie 1596",
    "Jokelantie 1653",
    "Jokelantie 1654",
    "Jokelantie 1675",
    "Jokelantie 1684",
    "Jokelantie 1752",
    "Jokelantie 1808",
    "Jokelantie 1995",
    "Jokelantie",
    "Jokelantörmäntie 15",
    "Jokelantörmäntie 27",
    "Jokelantörmäntie 29",
    "Jokelantörmäntie 43",
    "Jokelantörmäntie",
    "Jokilammentie 5",
    "Jokilammentie 620",
    "Jokilammentie 654",
    "Jokilammentie",
    "Juomujoentie 26",
    "Juomujoentie 46",
    "Juomujoentie 54",
    "Juomujoentie 70",
    "Juomujoentie",
    "Juomukuja 26",
    "Juomukuja",
    "Kampsajärventie 64",
    "Kampsajärventie",
    "Kampsavaaranpolku",
    "Kampsavaarantie",
    "Karhuhaantie 13",
    "Karhuhaantie 14",
    "Karhuhaantie 18",
    "Karhuhaantie 21",
    "Karhuhaantie 24",
    "Karhuhaantie",
    "Koulunraitti 9",
    "Koulunraitti 15",
    "Koulunraitti 21",
    "Koulunraitti 25",
    "Koulunraitti 27",
    "Koulunraitti 33",
    "Koulunraitti 34",
    "Koulunraitti 36",
    "Koulunraitti",
    "Kuohungintie 90",
    "Kuohungintie 105",
    "Kuohungintie",
    "Kuusikkokummuntie",
    "Lustilantie 32",
    "Lustilantie 53",
    "Lustilantie 130",
    "Lustilantie",
    "Marjapalonraitti 5",
    "Marjapalonraitti 34",
    "Marjapalonraitti 35",
    "Marjapalonraitti",
    "Mustonojantie 131",
    "Mustonojantie",
    "Narkausniementie 28",
    "Narkausniementie 33",
    "Narkausniementie 34",
    "Narkausniementie 44",
    "Narkausniementie 49",
    "Narkausniementie 62",
    "Narkausniementie 68",
    "Narkausniementie 107",
    "Narkausniementie",
    "Oudonkuja 20",
    "Oudonkuja 21",
    "Oudonkuja 27",
    "Oudonkuja",
    "Pikkuniementie 40",
    "Pikkuniementie 62",
    "Pikkuniementie",
    "Ranuantie 3018",
    "Ranuantie 3127",
    "Ranuantie 3135",
    "Ranuantie 3246",
    "Ranuantie 3271",
    "Ranuantie 3398",
    "Ranuantie 3416",
    "Ranuantie 3417",
    "Ranuantie 3441",
    "Ranuantie 3461",
    "Ranuantie 3687",
    "Ranuantie",
    "Särkilammentie 51",
    "Särkilammentie 67",
    "Särkilammentie 81",
    "Särkilammentie 105",
    "Särkilammentie 109",
    "Särkilammentie 128",
    "Särkilammentie 129",
    "Särkilammentie",
    "Tikankontti 59",
    "Tikankontti 77",
    "Tikankontti",
    "Tommilanmutka 13",
    "Tommilanmutka",
    "Vaskitie 52",
    "Vaskitie",
    "Veittikankaantie 9",
    "Veittikankaantie 28",
    "Veittikankaantie 40",
    "Veittikankaantie",
    "Veittivaarantie 51",
    "Veittivaarantie 98",
    "Veittivaarantie 105",
    "Veittivaarantie 188",
    "Veittivaarantie 223",
    "Veittivaarantie",
    "Vilmiläntie 13",
    "Vilmiläntie 14",
    "Vilmiläntie 38",
    "Vilmiläntie 58",
    "Vilmiläntie 84",
    "Vilmiläntie 114",
    "Vilmiläntie",
    "Ylikörköntie 1937",
    "Ylikörköntie 2223",
    "Ylikörköntie 2229",
    "Ylikörköntie 2231",
    "Ylikörköntie 2331",
    "Ylikörköntie 2383",
    "Ylikörköntie 2455",
    "Ylikörköntie 2456",
    "Ylikörköntie 2505",
    "Ylikörköntie 2534",
    "Ylikörköntie"
  ],
  "count": 171,
  "has_postboxes": false,
  "scraped_at": "2026-03-24T07:44:51.085Z",
  "success": true
}